proguard_rate/__init__.py
proguard_rate/__main__.py
proguard_rate-0.2.0.dist-info/LICENSE
proguard_rate-0.2.0.dist-info/METADATA
proguard_rate-0.2.0.dist-info/WHEEL
proguard_rate-0.2.0.dist-info/entry_points.txt
proguard_rate-0.2.0.dist-info/top_level.txt
proguard_rate-0.2.0.dist-info/RECORD
