Metadata-Version: 2.1
Name: proguard_rate
Version: 0.2.0
Summary: 计算代码混淆率
Home-page: https://github.com/weidongjian/proguardRate
Author: weidongjian
Author-email: weidongjian@gmail.com
License: UNKNOWN
Project-URL: Bug Tracker, https://github.com/weidongjian/proguardRate/issues
Platform: UNKNOWN
Classifier: Programming Language :: Python :: 3
Classifier: License :: OSI Approved :: MIT License
Classifier: Operating System :: OS Independent
Requires-Python: >=3.6
License-File: LICENSE
